jumpstarter_driver_flashers/__init__.py
jumpstarter_driver_flashers/bundle.py
jumpstarter_driver_flashers/client.py
jumpstarter_driver_flashers/client_test.py
jumpstarter_driver_flashers/driver.py
jumpstarter_driver_flashers/driver_test.py
jumpstarter_driver_flashers/test_bundle.py
jumpstarter_driver_flashers-0.7.4.dist-info/METADATA
jumpstarter_driver_flashers-0.7.4.dist-info/WHEEL
jumpstarter_driver_flashers-0.7.4.dist-info/RECORD
