Metadata-Version: 2.4
Name: jumpstarter-driver-flashers
Version: 0.7.4
Summary: Jumpstarter software defined flasher driver
Project-URL: Homepage, https://jumpstarter.dev
Project-URL: source_archive, https://github.com/jumpstarter-dev/repo/archive/c5d38de69eadbb8eb0388bcfe3430a679fff0059.zip
Author-email: Benny Zlotnik <bzlotnik@redhat.com>, Miguel Angel Ajo <majopela@redhat.com>
License-Expression: Apache-2.0
Requires-Python: >=3.11
Requires-Dist: anyio>=4.10.0
Requires-Dist: jumpstarter-driver-http==0.7.4
Requires-Dist: jumpstarter-driver-opendal==0.7.4
Requires-Dist: jumpstarter-driver-power==0.7.4
Requires-Dist: jumpstarter-driver-pyserial==0.7.4
Requires-Dist: jumpstarter-driver-tftp==0.7.4
Requires-Dist: jumpstarter-driver-uboot==0.7.4
Requires-Dist: jumpstarter==0.7.4
Requires-Dist: oras>=0.2.25
